flask_modals/__init__.py
flask_modals/modal.py
flask_modals/partial.py
flask_modals/static/css/progressBarStyle.css
flask_modals/static/js/main.js
flask_modals/templates/modals/jstemplate.html
flask_modals/templates/modals/modalMessages.html
flask_modals/templates/modals/nprogress.html
Flask_Modals-0.5.1.dist-info/LICENSE
Flask_Modals-0.5.1.dist-info/METADATA
Flask_Modals-0.5.1.dist-info/WHEEL
Flask_Modals-0.5.1.dist-info/top_level.txt
Flask_Modals-0.5.1.dist-info/RECORD
